wikitree_api/__init__.py
wikitree_api/__main__.py
wikitree_api/exceptions.py
wikitree_api/fields_reference.py
wikitree_api/session.py
wikitree_api/utils.py
wikitree_api-0.1.0b1.dist-info/licenses/LICENSE
wikitree_api-0.1.0b1.dist-info/METADATA
wikitree_api-0.1.0b1.dist-info/WHEEL
wikitree_api-0.1.0b1.dist-info/entry_points.txt
wikitree_api-0.1.0b1.dist-info/top_level.txt
wikitree_api-0.1.0b1.dist-info/RECORD
