Metadata-Version: 2.4
Name: wikitree-api
Version: 0.1.0b1
Summary: Python client for the WikiTree API
Author-email: Steven Harris <steven@harrislineage.com>
License-Expression: GPL-3.0-only
Project-URL: Homepage, https://github.com/harrislineage/wikitree-api-python
Project-URL: Repository, https://github.com/harrislineage/wikitree-api-python
Project-URL: Issues, https://github.com/harrislineage/wikitree-api-python/issues
Keywords: wikitree,api,client,genealogy
Requires-Python: >=3.8
License-File: LICENSE
Requires-Dist: requests>=2.28
Dynamic: license-file
